Basilisk/architecturelib.dll
Basilisk/architectureLib.lib
Basilisk/ArchitectureUtilities.lib
Basilisk/cMsgCInterface.lib
Basilisk/communicationlib.dll
Basilisk/communicationLib.lib
Basilisk/dynamicslib.dll
Basilisk/dynamicsLib.lib
Basilisk/effectorinterfaceslib.dll
Basilisk/effectorInterfacesLib.lib
Basilisk/environmentlib.dll
Basilisk/environmentLib.lib
Basilisk/moduleidgenerator.dll
Basilisk/mujoco.dll
Basilisk/mujocodynamicslib.dll
Basilisk/mujocoDynamicsLib.lib
Basilisk/onboarddatahandlinglib.dll
Basilisk/onboardDataHandlingLib.lib
Basilisk/powerlib.dll
Basilisk/powerLib.lib
Basilisk/transdeterminationlib.dll
Basilisk/transDeterminationLib.lib
Basilisk/vizardlib.dll
Basilisk/vizardLib.lib
Basilisk/vizMessage.lib
Basilisk/__init__.py
Basilisk/architecture/alg_contain.lib
Basilisk/architecture/alg_contain.py
Basilisk/architecture/astroConstants.lib
Basilisk/architecture/astroConstants.py
Basilisk/architecture/avsLibrarySelfCheck.lib
Basilisk/architecture/avsLibrarySelfCheck.py
Basilisk/architecture/bskLogging.lib
Basilisk/architecture/bskLogging.py
Basilisk/architecture/bskUtilities.lib
Basilisk/architecture/bskUtilities.py
Basilisk/architecture/BSpline.lib
Basilisk/architecture/BSpline.py
Basilisk/architecture/cSysModel.py
Basilisk/architecture/keplerianOrbit.lib
Basilisk/architecture/keplerianOrbit.py
Basilisk/architecture/moduleIdGenerator.lib
Basilisk/architecture/moduleIdGenerator.py
Basilisk/architecture/py_sys_model.lib
Basilisk/architecture/sim_model.lib
Basilisk/architecture/sim_model.py
Basilisk/architecture/swigDeprecatedCheck.lib
Basilisk/architecture/swigDeprecatedCheck.py
Basilisk/architecture/swigEigenCheck.lib
Basilisk/architecture/swigEigenCheck.py
Basilisk/architecture/swig_common_model.lib
Basilisk/architecture/swig_common_model.py
Basilisk/architecture/swig_conly_data.lib
Basilisk/architecture/swig_conly_data.py
Basilisk/architecture/swig_c_wrap.lib
Basilisk/architecture/swig_c_wrap.py
Basilisk/architecture/swig_deprecated.lib
bsk-2.9.0.dist-info/DELVEWHEEL
bsk-2.9.0.dist-info/entry_points.txt
bsk-2.9.0.dist-info/METADATA
bsk-2.9.0.dist-info/RECORD
bsk-2.9.0.dist-info/top_level.txt
bsk-2.9.0.dist-info/WHEEL
bsk-2.9.0.dist-info/licenses/LICENSE
