Metadata-Version: 2.4
Name: bsk
Version: 2.9.0
Summary: Basilisk: an Astrodynamics Simulation Framework
Home-page: https://avslab.github.io/basilisk/
License: 
Project-URL: homepage, https://avslab.github.io/basilisk/
Project-URL: source, https://github.com/AVSLab/basilisk
Project-URL: tracker, https://github.com/AVSLab/basilisk/issues
Requires-Python: <3.14,>=3.8
License-File: LICENSE
Requires-Dist: pandas<=2.2.3,>=2.0.3; python_version < "3.9"
Requires-Dist: pandas<=2.3.3,>=2.0.3; python_version >= "3.9"
Requires-Dist: matplotlib<=3.10.7,>=3.7.5
Requires-Dist: numpy<2.4.0,>=1.24.4; python_version < "3.13"
Requires-Dist: numpy<2.4.0,>=2.0; python_version >= "3.13"
Requires-Dist: colorama==0.4.6
Requires-Dist: tqdm==4.67.1
Requires-Dist: pillow<=12.0.0,>=10.4.0
Requires-Dist: requests<=2.32.5,>=2.32.3
Requires-Dist: bokeh<=3.8.1,>=3.1.1
Requires-Dist: protobuf<=6.33.1,>=5.29.4
Requires-Dist: pooch<1.9,>=1.7.0
Provides-Extra: test
Requires-Dist: psutil; extra == "test"
Requires-Dist: pytest-error-for-skips; extra == "test"
Requires-Dist: pytest; extra == "test"
Dynamic: home-page
Dynamic: license-file
